kthread/__init__.py
kthread-0.2.3.dist-info/LICENSE
kthread-0.2.3.dist-info/METADATA
kthread-0.2.3.dist-info/WHEEL
kthread-0.2.3.dist-info/top_level.txt
kthread-0.2.3.dist-info/RECORD
