Metadata-Version: 2.1
Name: kthread
Version: 0.2.3
Summary: Killable threads in Python!
Home-page: https://github.com/munshigroup/kthread
Author: The Munshi Group
Author-email: support@munshigroup.com
License: UNKNOWN
Keywords: threading threads terminate
Platform: UNKNOWN
Classifier: Programming Language :: Python :: 3
Classifier: Programming Language :: Python :: 2.7
Classifier: License :: OSI Approved :: MIT License
Classifier: Operating System :: OS Independent
License-File: LICENSE
